coder_dojo_common_python/__init__.py
coder_dojo_common_python-0.0.2.dist-info/WHEEL
coder_dojo_common_python-0.0.2.dist-info/METADATA
coder_dojo_common_python-0.0.2.dist-info/RECORD
