Metadata-Version: 2.1
Name: coder-dojo-common-python
Version: 0.0.2
Summary: Common packages for coder dojo sessions
Author: Stedders
Author-email: 3862686+Stedders@users.noreply.github.com
Requires-Python: >=3.8,<3.11
Classifier: Programming Language :: Python :: 3
Classifier: Programming Language :: Python :: 3.8
Classifier: Programming Language :: Python :: 3.9
Classifier: Programming Language :: Python :: 3.10
Provides-Extra: data
Provides-Extra: games
Requires-Dist: jupyterlab (>=3.5.2,<4.0.0) ; extra == "data"
Requires-Dist: matplotlib (>=3.6.3,<4.0.0) ; extra == "data"
Requires-Dist: numpy (>=1.24.1,<2.0.0) ; extra == "data"
Requires-Dist: pandas (>=1.5.2,<2.0.0) ; extra == "data"
Requires-Dist: pgzero (>=1.2.1,<2.0.0) ; extra == "games"
Requires-Dist: plotly (>=5.12.0,<6.0.0) ; extra == "data"
Requires-Dist: pygame (>=2.1.2,<3.0.0) ; extra == "games"
